pynamodb_single_table/__init__.py
pynamodb_single_table/base.py
pynamodb_single_table/py.typed
pynamodb_single_table-0.1.3.dist-info/LICENSE
pynamodb_single_table-0.1.3.dist-info/METADATA
pynamodb_single_table-0.1.3.dist-info/WHEEL
pynamodb_single_table-0.1.3.dist-info/entry_points.txt
pynamodb_single_table-0.1.3.dist-info/RECORD
