Metadata-Version: 2.1
Name: pynamodb_single_table
Version: 0.1.3
Summary: PynamoDB Single Table
Home-page: https://github.com/scnerd/pynamodb_single_table
License: MIT
Author: David Maxson
Author-email: scnerd@gmail.com
Requires-Python: >=3.7,<4.0
Classifier: Development Status :: 1 - Planning
Classifier: License :: OSI Approved :: MIT License
Classifier: Programming Language :: Python :: 3
Classifier: Programming Language :: Python :: 3.7
Classifier: Programming Language :: Python :: 3.8
Classifier: Programming Language :: Python :: 3.9
Classifier: Programming Language :: Python :: 3.10
Classifier: Programming Language :: Python :: 3.11
Classifier: Programming Language :: Python :: 3.12
Requires-Dist: pydantic (>=2)
Requires-Dist: pynamodb
Requires-Dist: pynamodb-attributes
Project-URL: Changelog, https://github.com/scnerd/pynamodb_single_table/releases
Project-URL: Documentation, https://pynamodb_single_table.readthedocs.io
Project-URL: Repository, https://github.com/scnerd/pynamodb_single_table
